subcat/__init__.py
subcat/cache.py
subcat/config.py
subcat/detector.py
subcat/fingerprints.json
subcat/logger.py
subcat/navigator.py
subcat/output.py
subcat/subcat.py
subcat/modules/alienvault.py
subcat/modules/anubis.py
subcat/modules/bevigil.py
subcat/modules/binaryedge.py
subcat/modules/censys.py
subcat/modules/certspotter.py
subcat/modules/chaos.py
subcat/modules/ctrsh.py
subcat/modules/digitalyama.py
subcat/modules/dnsarchive.py
subcat/modules/dnsdumpster.py
subcat/modules/hackertarget.py
subcat/modules/netlas.py
subcat/modules/securitytrails.py
subcat/modules/shodan.py
subcat/modules/threatcrowd.py
subcat/modules/urlscan.py
subcat/modules/virustotal.py
subcat/modules/wayback.py
subcat-1.4.0.dist-info/METADATA
subcat-1.4.0.dist-info/WHEEL
subcat-1.4.0.dist-info/entry_points.txt
subcat-1.4.0.dist-info/top_level.txt
subcat-1.4.0.dist-info/RECORD
