Metadata-Version: 2.4
Name: subcat
Version: 1.4.0
Summary: Lightning-fast passive subdomain discovery tool for security professionals and bug bounty hunters.
Home-page: https://github.com/duty1g/subcat
Author: duty1g
Author-email: sec@dzauth.com
License: MIT
Classifier: Programming Language :: Python :: 3
Classifier: License :: OSI Approved :: MIT License
Classifier: Operating System :: OS Independent
Requires-Python: >=3.6
Requires-Dist: requests>=2.25.0
Requires-Dist: PyYAML>=5.4.0
